opendatalab/__init__.py
opendatalab/__version__.py
opendatalab/api.py
opendatalab/client.py
opendatalab/dataset.py
opendatalab/download.py
opendatalab/exceptions.py
opendatalab/utils.py
opendatalab_python_sdk-0.0.4.dist-info/METADATA
opendatalab_python_sdk-0.0.4.dist-info/WHEEL
opendatalab_python_sdk-0.0.4.dist-info/top_level.txt
opendatalab_python_sdk-0.0.4.dist-info/RECORD
