Metadata-Version: 2.1
Name: opendatalab-python-sdk
Version: 0.0.4
Summary: Python SDK for reading dataset files.
Home-page: https://gitlab.shlab.tech/dps/opendatalab-python-sdk
Author: Zhang Chaobin, Wang Rui
Author-email: zhangchaobin@sensetime.com, wangrui@pjlab.org.cn
License: UNKNOWN
Project-URL: Bug Tracker, https://gitlab.shlab.tech/dps/opendatalab-python-sdk/-/issues
Platform: UNKNOWN
Classifier: Development Status :: 3 - Alpha
Classifier: Intended Audience :: Developers
Classifier: Topic :: Software Development :: Build Tools
Classifier: Programming Language :: Python :: 3
Classifier: License :: OSI Approved :: MIT License
Classifier: Operating System :: OS Independent
Requires-Python: >=3.6
Requires-Dist: requests
Requires-Dist: oss2
Requires-Dist: Click
Requires-Dist: tqdm
